litcommit/library.py
litcommit/main.py
litcommit-0.1.23.dist-info/entry_points.txt
litcommit-0.1.23.dist-info/WHEEL
litcommit-0.1.23.dist-info/METADATA
litcommit-0.1.23.dist-info/RECORD
