Metadata-Version: 2.1
Name: litcommit
Version: 0.1.23
Summary: No more commenting your code: Use the GPT3-based CodeCommenter
Author: Standard Data, Inc.
Author-email: contact@standarddata.ai
Requires-Python: >=3.7,<4.0
Classifier: Programming Language :: Python :: 3
Classifier: Programming Language :: Python :: 3.10
Classifier: Programming Language :: Python :: 3.7
Classifier: Programming Language :: Python :: 3.8
Classifier: Programming Language :: Python :: 3.9
Requires-Dist: GitPython (>=3.1.27,<4.0.0)
Requires-Dist: click (>=8.1.3,<9.0.0)
Requires-Dist: requests (>=2.27.1,<3.0.0)
Requires-Dist: typer (>=0.4.1,<0.5.0)
